spiraleval/__init__.py
spiraleval/generate.py
spiraleval/llm.py
spiraleval/llmTrial.py
spiraleval/spiralEval.py
spiraleval/summary.py
SpiralEval-0.1.1.dist-info/LICENSE
SpiralEval-0.1.1.dist-info/METADATA
SpiralEval-0.1.1.dist-info/WHEEL
SpiralEval-0.1.1.dist-info/top_level.txt
SpiralEval-0.1.1.dist-info/RECORD
