Metadata-Version: 2.1
Name: SpiralEval
Version: 0.1.1
Summary: Evaluation for characteristics
Home-page: https://github.com/Spiral-AI/SpiralEval
Author: Kosei Uemura
Author-email: koseiuemura1227@gmail.com
Keywords: openai,api,evaluation,characteristics,gpt
Classifier: Development Status :: 3 - Alpha
Classifier: Intended Audience :: Developers
Classifier: Topic :: Scientific/Engineering :: Information Analysis
Classifier: License :: OSI Approved :: MIT License
Classifier: Programming Language :: Python :: 3.8
Classifier: Programming Language :: Python :: 3.9
Classifier: Programming Language :: Python :: 3.10
Requires-Python: >=3.8, <4
License-File: LICENSE
Requires-Dist: openai
Requires-Dist: pandas
